Metadata-Version: 1.1
Name: GEDIpy
Version: 0.0
Summary: GEDIpy is a Python Package for NASA's Global Ecosystem Dynamics Investigation (GEDI) mission data extraction, analysis,processing and visualization.
Home-page: https://github.com/EduinHSERNA/pygedi
Author: Eduin
Author-email: eduin@sigma.blue
License: LGPL v3
Keywords: GEDI
Platform: UNKNOWN
Classifier: Programming Language :: Python
